[
  {
    "ContainingType": "devtrack.Controllers.AuthController",
    "Method": "LoginAsync",
    "RelativePath": "api/Auth/login",
    "HttpMethod": "POST",
    "IsController": true,
    "Order": 0,
    "Parameters": [
      {
        "Name": "login",
        "Type": "devtrack.Controllers.LoginDto",
        "IsRequired": true
      }
    ],
    "ReturnTypes": []
  },
  {
    "ContainingType": "devtrack.Controllers.MandorProjectController",
    "Method": "GetAll",
    "RelativePath": "api/MandorProject",
    "HttpMethod": "GET",
    "IsController": true,
    "Order": 0,
    "Parameters": [],
    "ReturnTypes": [
      {
        "Type": "System.Collections.Generic.IEnumerable\u00601[[devtrack.Models.MandorProject, devtrack, Version=1.0.0.0, Culture=neutral, PublicKeyToken=null]]",
        "MediaTypes": [
          "text/plain",
          "application/json",
          "text/json"
        ],
        "StatusCode": 200
      }
    ]
  },
  {
    "ContainingType": "devtrack.Controllers.MandorProjectController",
    "Method": "GetById",
    "RelativePath": "api/MandorProject/{id}",
    "HttpMethod": "GET",
    "IsController": true,
    "Order": 0,
    "Parameters": [
      {
        "Name": "id",
        "Type": "System.Int32",
        "IsRequired": true
      }
    ],
    "ReturnTypes": [
      {
        "Type": "devtrack.Models.MandorProject",
        "MediaTypes": [
          "text/plain",
          "application/json",
          "text/json"
        ],
        "StatusCode": 200
      }
    ]
  },
  {
    "ContainingType": "devtrack.Controllers.MandorProjectProjectController",
    "Method": "GetAll",
    "RelativePath": "api/MandorProjectProject",
    "HttpMethod": "GET",
    "IsController": true,
    "Order": 0,
    "Parameters": [],
    "ReturnTypes": []
  },
  {
    "ContainingType": "devtrack.Controllers.MandorProjectProjectController",
    "Method": "GetById",
    "RelativePath": "api/MandorProjectProject/{id}",
    "HttpMethod": "GET",
    "IsController": true,
    "Order": 0,
    "Parameters": [
      {
        "Name": "id",
        "Type": "System.Int32",
        "IsRequired": true
      }
    ],
    "ReturnTypes": []
  },
  {
    "ContainingType": "devtrack.Controllers.MandorProjectProjectController",
    "Method": "Create",
    "RelativePath": "api/MandorProjectProject/assign",
    "HttpMethod": "POST",
    "IsController": true,
    "Order": 0,
    "Parameters": [
      {
        "Name": "mpp",
        "Type": "devtrack.Models.MandorProjectProject",
        "IsRequired": true
      }
    ],
    "ReturnTypes": []
  },
  {
    "ContainingType": "devtrack.Controllers.MandorProjectProjectController",
    "Method": "GetByUser",
    "RelativePath": "api/MandorProjectProject/byMandor",
    "HttpMethod": "GET",
    "IsController": true,
    "Order": 0,
    "Parameters": [],
    "ReturnTypes": []
  },
  {
    "ContainingType": "devtrack.Controllers.ProjectController",
    "Method": "GetAllProjects",
    "RelativePath": "api/Project",
    "HttpMethod": "GET",
    "IsController": true,
    "Order": 0,
    "Parameters": [],
    "ReturnTypes": []
  },
  {
    "ContainingType": "devtrack.Controllers.ProjectController",
    "Method": "GetProject",
    "RelativePath": "api/Project/{id}",
    "HttpMethod": "GET",
    "IsController": true,
    "Order": 0,
    "Parameters": [
      {
        "Name": "id",
        "Type": "System.Int32",
        "IsRequired": true
      }
    ],
    "ReturnTypes": []
  },
  {
    "ContainingType": "devtrack.Controllers.ProjectController",
    "Method": "Create",
    "RelativePath": "api/Project/create",
    "HttpMethod": "POST",
    "IsController": true,
    "Order": 0,
    "Parameters": [
      {
        "Name": "project",
        "Type": "devtrack.Models.Project",
        "IsRequired": true
      }
    ],
    "ReturnTypes": []
  },
  {
    "ContainingType": "devtrack.Controllers.ProjectController",
    "Method": "EditProject",
    "RelativePath": "api/Project/edit/{id}",
    "HttpMethod": "PUT",
    "IsController": true,
    "Order": 0,
    "Parameters": [
      {
        "Name": "id",
        "Type": "System.Int32",
        "IsRequired": true
      },
      {
        "Name": "updatedProject",
        "Type": "devtrack.Models.Project",
        "IsRequired": true
      }
    ],
    "ReturnTypes": []
  },
  {
    "ContainingType": "devtrack.Controllers.ReportController",
    "Method": "GetById",
    "RelativePath": "api/Report/{id}",
    "HttpMethod": "GET",
    "IsController": true,
    "Order": 0,
    "Parameters": [
      {
        "Name": "id",
        "Type": "System.Int32",
        "IsRequired": true
      }
    ],
    "ReturnTypes": []
  },
  {
    "ContainingType": "devtrack.Controllers.ReportController",
    "Method": "GetAllReports",
    "RelativePath": "api/Report/all",
    "HttpMethod": "GET",
    "IsController": true,
    "Order": 0,
    "Parameters": [],
    "ReturnTypes": []
  },
  {
    "ContainingType": "devtrack.Controllers.ReportController",
    "Method": "GetByProjectId",
    "RelativePath": "api/Report/byProject/{projectId}",
    "HttpMethod": "GET",
    "IsController": true,
    "Order": 0,
    "Parameters": [
      {
        "Name": "projectId",
        "Type": "System.Int32",
        "IsRequired": true
      }
    ],
    "ReturnTypes": []
  },
  {
    "ContainingType": "devtrack.Controllers.ReportController",
    "Method": "DeleteReport",
    "RelativePath": "api/Report/delete/{id}",
    "HttpMethod": "DELETE",
    "IsController": true,
    "Order": 0,
    "Parameters": [
      {
        "Name": "id",
        "Type": "System.Int32",
        "IsRequired": true
      }
    ],
    "ReturnTypes": []
  },
  {
    "ContainingType": "devtrack.Controllers.ReportController",
    "Method": "EditReport",
    "RelativePath": "api/Report/edit/{id}",
    "HttpMethod": "PUT",
    "IsController": true,
    "Order": 0,
    "Parameters": [
      {
        "Name": "id",
        "Type": "System.Int32",
        "IsRequired": true
      },
      {
        "Name": "updatedReport",
        "Type": "devtrack.Models.UpdateReportDTO",
        "IsRequired": true
      }
    ],
    "ReturnTypes": []
  },
  {
    "ContainingType": "devtrack.Controllers.ReportController",
    "Method": "SubmitReport",
    "RelativePath": "api/Report/submit",
    "HttpMethod": "POST",
    "IsController": true,
    "Order": 0,
    "Parameters": [
      {
        "Name": "report",
        "Type": "devtrack.Models.Report",
        "IsRequired": true
      }
    ],
    "ReturnTypes": []
  },
  {
    "ContainingType": "devtrack.Controllers.RiwayatController",
    "Method": "AddRiwayat",
    "RelativePath": "api/Riwayat/add-riwayat",
    "HttpMethod": "POST",
    "IsController": true,
    "Order": 0,
    "Parameters": [
      {
        "Name": "newRiwayat",
        "Type": "devtrack.Models.Riwayat",
        "IsRequired": true
      }
    ],
    "ReturnTypes": []
  },
  {
    "ContainingType": "devtrack.Controllers.RiwayatController",
    "Method": "ViewRiwayat",
    "RelativePath": "api/Riwayat/view",
    "HttpMethod": "GET",
    "IsController": true,
    "Order": 0,
    "Parameters": [],
    "ReturnTypes": []
  },
  {
    "ContainingType": "devtrack.Controllers.UserManagementController",
    "Method": "AddMandor",
    "RelativePath": "api/UserManagement/add-mandor",
    "HttpMethod": "POST",
    "IsController": true,
    "Order": 0,
    "Parameters": [
      {
        "Name": "mandor",
        "Type": "devtrack.Models.User",
        "IsRequired": true
      }
    ],
    "ReturnTypes": []
  },
  {
    "ContainingType": "devtrack.Controllers.UserManagementController",
    "Method": "EditMandor",
    "RelativePath": "api/UserManagement/edit-mandor/{id}",
    "HttpMethod": "PUT",
    "IsController": true,
    "Order": 0,
    "Parameters": [
      {
        "Name": "id",
        "Type": "System.Int32",
        "IsRequired": true
      },
      {
        "Name": "updatedMandor",
        "Type": "devtrack.Models.User",
        "IsRequired": true
      }
    ],
    "ReturnTypes": []
  },
  {
    "ContainingType": "devtrack.Controllers.UserManagementController",
    "Method": "EditPassword",
    "RelativePath": "api/UserManagement/edit-password",
    "HttpMethod": "PUT",
    "IsController": true,
    "Order": 0,
    "Parameters": [
      {
        "Name": "model",
        "Type": "devtrack.Controllers.UserManagementController\u002BChangePasswordDto",
        "IsRequired": true
      }
    ],
    "ReturnTypes": []
  },
  {
    "ContainingType": "devtrack.Controllers.UserManagementController",
    "Method": "GetMandor",
    "RelativePath": "api/UserManagement/mandor",
    "HttpMethod": "GET",
    "IsController": true,
    "Order": 0,
    "Parameters": [],
    "ReturnTypes": []
  },
  {
    "ContainingType": "devtrack.Controllers.UserManagementController",
    "Method": "GetMandorById",
    "RelativePath": "api/UserManagement/mandor/{id}",
    "HttpMethod": "GET",
    "IsController": true,
    "Order": 0,
    "Parameters": [
      {
        "Name": "id",
        "Type": "System.Int32",
        "IsRequired": true
      }
    ],
    "ReturnTypes": []
  },
  {
    "ContainingType": "devtrack.Controllers.UserManagementController",
    "Method": "ToogleStatus",
    "RelativePath": "api/UserManagement/ToggleStatus/{id}",
    "HttpMethod": "PUT",
    "IsController": true,
    "Order": 0,
    "Parameters": [
      {
        "Name": "id",
        "Type": "System.Int32",
        "IsRequired": true
      }
    ],
    "ReturnTypes": []
  }
]